morphium/__init__.py
morphium/archive.py
morphium/ia.py
morphium/util.py
morphium-0.2.0.dist-info/DESCRIPTION.rst
morphium-0.2.0.dist-info/METADATA
morphium-0.2.0.dist-info/RECORD
morphium-0.2.0.dist-info/WHEEL
morphium-0.2.0.dist-info/metadata.json
morphium-0.2.0.dist-info/namespace_packages.txt
morphium-0.2.0.dist-info/top_level.txt
