Metadata-Version: 2.0
Name: morphium
Version: 0.2.0
Summary: Tools for scrapers on morph.io
Home-page: http://github.com/pudo/morphium
Author: Friedrich Lindenberg
Author-email: friedrich@pudo.org
License: MIT
Keywords: data scrapers
Platform: UNKNOWN
Classifier: Development Status :: 3 - Alpha
Classifier: Intended Audience :: Developers
Classifier: License :: OSI Approved :: MIT License
Classifier: Operating System :: OS Independent
Classifier: Programming Language :: Python :: 2.7
Classifier: Programming Language :: Python :: 3.3
Requires-Dist: normality (>=0.2.2)
Requires-Dist: six (>=1.7.3)
Requires-Dist: boto3
Requires-Dist: boto
